<?xml version="1.0" encoding="utf-8" ?>
<Advertisements>
    <Ad>
        <ImageUrl>images/CS101.gif</ImageUrl>
        <Width>140</Width>
        <Height>190</Height>
        <NavigateUrl>Details.aspx?No=CS101</NavigateUrl>
        <AlternateText>CS101</AlternateText>
        <Keyword>Concept</Keyword>
        <Impressions>25</Impressions>
        <Caption>計算機概論</Caption>
    </Ad>
    <Ad>
        <ImageUrl>images/CS121.gif</ImageUrl>
        <Width>140</Width>
        <Height>190</Height>
        <NavigateUrl>Details.aspx?No=CS121</NavigateUrl>
        <AlternateText>CS121</AlternateText>
        <Keyword>Concept</Keyword>
        <Impressions>50</Impressions>
        <Caption>離散數學</Caption>
    </Ad>
    <Ad>
        <ImageUrl>images/CS203.gif</ImageUrl>
        <Width>140</Width>
        <Height>190</Height>
        <NavigateUrl>Details.aspx?No=CS203</NavigateUrl>
        <AlternateText>CS203</AlternateText>
        <Keyword>Programming</Keyword>
        <Impressions>50</Impressions>
        <Caption>程式語言</Caption>
    </Ad>
    <Ad>
        <ImageUrl>images/CS213.gif</ImageUrl>
        <Width>140</Width>
        <Height>190</Height>
        <NavigateUrl>Details.aspx?No=CS213</NavigateUrl>
        <AlternateText>CS213</AlternateText>
        <Keyword>OOP</Keyword>
        <Impressions>50</Impressions>
        <Caption>物件導向程式設計</Caption>
    </Ad>
    <Ad>
        <ImageUrl>images/CS222.gif</ImageUrl>
        <Width>140</Width>
        <Height>190</Height>
        <NavigateUrl>Details.aspx?No=CS222</NavigateUrl>
        <AlternateText>CS222</AlternateText>
        <Keyword>Concept</Keyword>
        <Impressions>50</Impressions>
        <Caption>資料庫管理系統</Caption>
    </Ad>
</Advertisements>
